charmcraftlocal/__init__.py
charmcraftlocal/_main.py
charmcraftlocal-0.3.1.dist-info/LICENSE
charmcraftlocal-0.3.1.dist-info/METADATA
charmcraftlocal-0.3.1.dist-info/WHEEL
charmcraftlocal-0.3.1.dist-info/entry_points.txt
charmcraftlocal-0.3.1.dist-info/RECORD
