Metadata-Version: 2.3
Name: charmcraftlocal
Version: 0.3.1
Summary: Pack charms with local Python package dependencies
Author: Carl Csaposs
Author-email: carl.csaposs@canonical.com
Requires-Python: >=3.10
Classifier: Programming Language :: Python :: 3
Classifier: Programming Language :: Python :: 3.10
Classifier: Programming Language :: Python :: 3.11
Classifier: Programming Language :: Python :: 3.12
Classifier: Programming Language :: Python :: 3.13
Requires-Dist: charm-refresh-build-version (>=0.4.0)
Requires-Dist: pyyaml (>=6.0.2)
Requires-Dist: requests (>=2.32.4)
Requires-Dist: tomli (>=2.2.1)
Requires-Dist: typer (>=0.16.0)
Project-URL: Repository, https://github.com/canonical/charmcraftlocal
